quipudigital/__init__.py
quipudigital/main.py
quipudigital/utils.py
quipudigital/assets/end-knot.gif
quipudigital/assets/grid.gif
quipudigital/assets/long-knot-1.gif
quipudigital/assets/long-knot-2.gif
quipudigital/assets/long-knot-3.gif
quipudigital/assets/long-knot-4.gif
quipudigital/assets/long-knot-5.gif
quipudigital/assets/long-knot-6.gif
quipudigital/assets/long-knot-7.gif
quipudigital/assets/long-knot-8.gif
quipudigital/assets/long-knot-9.gif
quipudigital/assets/overhand-knot-1.gif
quipudigital/assets/overhand-knot-2.gif
quipudigital/assets/overhand-knot-3.gif
quipudigital/assets/overhand-knot-4.gif
quipudigital/assets/overhand-knot-5.gif
quipudigital/assets/overhand-knot-6.gif
quipudigital/assets/overhand-knot-7.gif
quipudigital/assets/overhand-knot-8.gif
quipudigital/assets/overhand-knot-9.gif
quipudigital/assets/pendant-cord.gif
quipudigital/assets/primary-cord.gif
quipudigital/assets/top-cord.gif
quipudigital/assets/top-grid.gif
quipudigital/assets/top-long-knot-1.gif
quipudigital/assets/top-long-knot-2.gif
quipudigital/assets/top-long-knot-3.gif
quipudigital/assets/top-long-knot-4.gif
quipudigital/assets/top-long-knot-5.gif
quipudigital/assets/top-long-knot-6.gif
quipudigital/assets/top-long-knot-7.gif
quipudigital/assets/top-long-knot-8.gif
quipudigital/assets/top-long-knot-9.gif
quipudigital/assets/top-overhand-knot-1.gif
quipudigital/assets/top-overhand-knot-2.gif
quipudigital/assets/top-overhand-knot-3.gif
quipudigital/assets/top-overhand-knot-4.gif
quipudigital/assets/top-overhand-knot-5.gif
quipudigital/assets/top-overhand-knot-6.gif
quipudigital/assets/top-overhand-knot-7.gif
quipudigital/assets/top-overhand-knot-8.gif
quipudigital/assets/top-overhand-knot-9.gif
quipudigital-0.1.5.dist-info/LICENSE
quipudigital-0.1.5.dist-info/METADATA
quipudigital-0.1.5.dist-info/WHEEL
quipudigital-0.1.5.dist-info/top_level.txt
quipudigital-0.1.5.dist-info/RECORD
