Metadata-Version: 2.1
Name: quipudigital
Version: 0.1.5
Summary: Una biblioteca de visualización de Quipus con Python
Home-page: https://github.com/jgomezz/quipudigital
Author: Jaime Gomez
Author-email: jgomezz@gmail.com
License-File: LICENSE
